[
  {
    "timestamp": "2025-10-07T08:32:12.370569",
    "latency_ms": 10.440995,
    "count": 30526,
    "cache_miss": false,
    "keyword": "the"
  },
  {
    "timestamp": "2025-10-07T08:32:12.384085",
    "latency_ms": 10.528704,
    "count": 28566,
    "cache_miss": false,
    "keyword": "and"
  },
  {
    "timestamp": "2025-10-07T08:32:12.397953",
    "latency_ms": 724.82282,
    "count": 38,
    "cache_miss": false,
    "keyword": "Roses"
  },
  {
    "timestamp": "2025-10-07T08:32:13.128046",
    "latency_ms": 2070.846505,
    "count": 57,
    "cache_miss": false,
    "keyword": "absence"
  },
  null,
  {
    "timestamp": "2025-10-07T08:32:19.768756",
    "latency_ms": 9719.265472,
    "count": 0,
    "cache_miss": false,
    "keyword": "Thine eyes"
  },
  {
    "timestamp": "2025-10-07T08:32:29.511309",
    "latency_ms": 171.903723,
    "count": 94,
    "cache_miss": false,
    "keyword": "cheek"
  },
  {
    "timestamp": "2025-10-07T08:32:29.776711",
    "latency_ms": 293.16865,
    "count": 2957,
    "cache_miss": false,
    "keyword": "she"
  },
  {
    "timestamp": "2025-10-07T08:32:30.104315",
    "latency_ms": 187.529912,
    "count": 30,
    "cache_miss": false,
    "keyword": "compare"
  },
  {
    "timestamp": "2025-10-07T08:32:30.357287",
    "latency_ms": 234.886207,
    "count": 14,
    "cache_miss": false,
    "keyword": "tyrannous"
  }
]