[
  {
    "timestamp": "2025-09-27T09:47:10.965583",
    "latency_ms": 20.373302,
    "count": 30526,
    "cache_miss": false,
    "keyword": "the"
  },
  {
    "timestamp": "2025-09-27T09:47:10.987966",
    "latency_ms": 18.966584,
    "count": 28566,
    "cache_miss": false,
    "keyword": "and"
  },
  {
    "timestamp": "2025-09-27T09:47:11.005159",
    "latency_ms": 14.394502,
    "count": 38,
    "cache_miss": false,
    "keyword": "Roses"
  },
  {
    "timestamp": "2025-09-27T09:47:11.020049",
    "latency_ms": 11.151631,
    "count": 57,
    "cache_miss": false,
    "keyword": "absence"
  },
  {
    "timestamp": "2025-09-27T09:47:11.035143",
    "latency_ms": 10.302261,
    "count": 4,
    "cache_miss": false,
    "keyword": "withering"
  },
  {
    "timestamp": "2025-09-27T09:47:11.048506",
    "latency_ms": 9.760115,
    "count": 0,
    "cache_miss": false,
    "keyword": "Thine eyes"
  },
  {
    "timestamp": "2025-09-27T09:47:11.063096",
    "latency_ms": 8.906444,
    "count": 94,
    "cache_miss": false,
    "keyword": "cheek"
  },
  {
    "timestamp": "2025-09-27T09:47:11.081527",
    "latency_ms": 15.623105,
    "count": 2957,
    "cache_miss": false,
    "keyword": "she"
  },
  {
    "timestamp": "2025-09-27T09:47:11.102568",
    "latency_ms": 15.343781,
    "count": 30,
    "cache_miss": false,
    "keyword": "compare"
  },
  {
    "timestamp": "2025-09-27T09:47:11.116550",
    "latency_ms": 10.937814,
    "count": 14,
    "cache_miss": false,
    "keyword": "tyrannous"
  }
]