[
  {
    "timestamp": "2025-09-27T09:46:33.819797",
    "latency_ms": 9.835722,
    "count": 30526,
    "cache_miss": false,
    "keyword": "the"
  },
  {
    "timestamp": "2025-09-27T09:46:33.831123",
    "latency_ms": 7.608536,
    "count": 28566,
    "cache_miss": false,
    "keyword": "and"
  },
  {
    "timestamp": "2025-09-27T09:46:33.843137",
    "latency_ms": 9.112361,
    "count": 38,
    "cache_miss": false,
    "keyword": "Roses"
  },
  {
    "timestamp": "2025-09-27T09:46:33.854864",
    "latency_ms": 9.064257,
    "count": 57,
    "cache_miss": false,
    "keyword": "absence"
  },
  {
    "timestamp": "2025-09-27T09:46:33.867872",
    "latency_ms": 9.951032,
    "count": 4,
    "cache_miss": false,
    "keyword": "withering"
  },
  {
    "timestamp": "2025-09-27T09:46:33.877740",
    "latency_ms": 6.551648,
    "count": 0,
    "cache_miss": false,
    "keyword": "Thine eyes"
  },
  {
    "timestamp": "2025-09-27T09:46:33.887447",
    "latency_ms": 7.65934,
    "count": 94,
    "cache_miss": false,
    "keyword": "cheek"
  },
  {
    "timestamp": "2025-09-27T09:46:34.814604",
    "latency_ms": 924.454447,
    "count": 2957,
    "cache_miss": false,
    "keyword": "she"
  },
  {
    "timestamp": "2025-09-27T09:46:35.845275",
    "latency_ms": 1028.460939,
    "count": 30,
    "cache_miss": false,
    "keyword": "compare"
  },
  {
    "timestamp": "2025-09-27T09:46:37.646208",
    "latency_ms": 1776.860229,
    "count": 14,
    "cache_miss": false,
    "keyword": "tyrannous"
  }
]