[
  {
    "timestamp": "2025-09-30T09:34:57.154155",
    "latency_ms": 11.389813,
    "count": 30526,
    "cache_miss": false,
    "keyword": "the"
  },
  {
    "timestamp": "2025-09-30T09:34:57.170533",
    "latency_ms": 11.706948,
    "count": 28566,
    "cache_miss": false,
    "keyword": "and"
  },
  {
    "timestamp": "2025-09-30T09:34:57.190876",
    "latency_ms": 17.270641,
    "count": 38,
    "cache_miss": false,
    "keyword": "Roses"
  },
  {
    "timestamp": "2025-09-30T09:34:57.205492",
    "latency_ms": 11.515528,
    "count": 57,
    "cache_miss": false,
    "keyword": "absence"
  },
  {
    "timestamp": "2025-09-30T09:34:57.221799",
    "latency_ms": 12.088689,
    "count": 4,
    "cache_miss": false,
    "keyword": "withering"
  },
  {
    "timestamp": "2025-09-30T09:34:57.248347",
    "latency_ms": 23.211774,
    "count": 0,
    "cache_miss": false,
    "keyword": "Thine eyes"
  },
  {
    "timestamp": "2025-09-30T09:34:57.270107",
    "latency_ms": 17.753692,
    "count": 94,
    "cache_miss": false,
    "keyword": "cheek"
  },
  {
    "timestamp": "2025-09-30T09:34:57.287701",
    "latency_ms": 14.343128,
    "count": 2957,
    "cache_miss": false,
    "keyword": "she"
  },
  {
    "timestamp": "2025-09-30T09:34:57.302069",
    "latency_ms": 11.017474,
    "count": 30,
    "cache_miss": false,
    "keyword": "compare"
  },
  {
    "timestamp": "2025-09-30T09:34:57.318331",
    "latency_ms": 12.821967,
    "count": 14,
    "cache_miss": false,
    "keyword": "tyrannous"
  }
]