[
  {
    "timestamp": "2025-10-01T17:51:36.125423",
    "latency_ms": 8.560216,
    "count": 30526,
    "cache_miss": false,
    "keyword": "the"
  },
  {
    "timestamp": "2025-10-01T17:51:36.136510",
    "latency_ms": 8.540515,
    "count": 28566,
    "cache_miss": false,
    "keyword": "and"
  },
  {
    "timestamp": "2025-10-01T17:51:36.147949",
    "latency_ms": 8.032654,
    "count": 38,
    "cache_miss": false,
    "keyword": "Roses"
  },
  {
    "timestamp": "2025-10-01T17:51:36.158457",
    "latency_ms": 8.305286,
    "count": 57,
    "cache_miss": false,
    "keyword": "absence"
  },
  {
    "timestamp": "2025-10-01T17:51:36.169180",
    "latency_ms": 7.627606,
    "count": 4,
    "cache_miss": false,
    "keyword": "withering"
  },
  {
    "timestamp": "2025-10-01T17:51:36.179515",
    "latency_ms": 822.823521,
    "count": 0,
    "cache_miss": false,
    "keyword": "Thine eyes"
  },
  {
    "timestamp": "2025-10-01T17:51:37.011424",
    "latency_ms": 926.936786,
    "count": 94,
    "cache_miss": false,
    "keyword": "cheek"
  },
  {
    "timestamp": "2025-10-01T17:51:37.949149",
    "latency_ms": 1042.550416,
    "count": 2957,
    "cache_miss": false,
    "keyword": "she"
  },
  {
    "timestamp": "2025-10-01T17:51:39.002652",
    "latency_ms": 1065.24097,
    "count": 30,
    "cache_miss": false,
    "keyword": "compare"
  },
  {
    "timestamp": "2025-10-01T17:51:40.071935",
    "latency_ms": 1237.829311,
    "count": 14,
    "cache_miss": false,
    "keyword": "tyrannous"
  }
]