[
  {
    "timestamp": "2025-10-08T19:57:34.959518",
    "latency_ms": 2054.177476,
    "count": 30526,
    "cache_miss": false,
    "keyword": "the"
  },
  {
    "timestamp": "2025-10-08T19:57:37.044677",
    "latency_ms": 1468.859181,
    "count": 28566,
    "cache_miss": false,
    "keyword": "and"
  },
  {
    "timestamp": "2025-10-08T19:57:38.520325",
    "latency_ms": 201.540101,
    "count": 2957,
    "cache_miss": false,
    "keyword": "she"
  },
  {
    "timestamp": "2025-10-08T19:57:38.744903",
    "latency_ms": 91.038576,
    "count": 94,
    "cache_miss": false,
    "keyword": "cheek"
  },
  {
    "timestamp": "2025-10-08T19:57:38.847509",
    "latency_ms": 44.551216,
    "count": 38,
    "cache_miss": false,
    "keyword": "Roses"
  },
  {
    "timestamp": "2025-10-08T19:57:38.901607",
    "latency_ms": 1186.688224,
    "count": 57,
    "cache_miss": false,
    "keyword": "absence"
  },
  {
    "timestamp": "2025-10-08T19:57:40.150361",
    "latency_ms": 244.812321,
    "count": 30,
    "cache_miss": false,
    "keyword": "compare"
  },
  {
    "timestamp": "2025-10-08T19:57:40.454244",
    "latency_ms": 149.342016,
    "count": 4,
    "cache_miss": false,
    "keyword": "withering"
  },
  {
    "timestamp": "2025-10-08T19:57:40.633661",
    "latency_ms": 116.239751,
    "count": 14,
    "cache_miss": false,
    "keyword": "tyrannous"
  },
  {
    "timestamp": "2025-10-08T19:57:40.780023",
    "latency_ms": 90.595243,
    "count": 0,
    "cache_miss": false,
    "keyword": "Thine eyes"
  }
]