[
  {
    "timestamp": "2025-10-08T19:58:11.555546",
    "latency_ms": 20.867281,
    "count": 30526,
    "cache_miss": false,
    "keyword": "the"
  },
  {
    "timestamp": "2025-10-08T19:58:11.578837",
    "latency_ms": 13.901286,
    "count": 28566,
    "cache_miss": false,
    "keyword": "and"
  },
  {
    "timestamp": "2025-10-08T19:58:11.595317",
    "latency_ms": 13.654162,
    "count": 2957,
    "cache_miss": false,
    "keyword": "she"
  },
  {
    "timestamp": "2025-10-08T19:58:11.611233",
    "latency_ms": 13.646861,
    "count": 94,
    "cache_miss": false,
    "keyword": "cheek"
  },
  {
    "timestamp": "2025-10-08T19:58:11.627823",
    "latency_ms": 16.931788,
    "count": 38,
    "cache_miss": false,
    "keyword": "Roses"
  },
  {
    "timestamp": "2025-10-08T19:58:11.647112",
    "latency_ms": 13.390535,
    "count": 57,
    "cache_miss": false,
    "keyword": "absence"
  },
  {
    "timestamp": "2025-10-08T19:58:11.663676",
    "latency_ms": 14.804676,
    "count": 30,
    "cache_miss": false,
    "keyword": "compare"
  },
  {
    "timestamp": "2025-10-08T19:58:11.680588",
    "latency_ms": 16.721968,
    "count": 4,
    "cache_miss": false,
    "keyword": "withering"
  },
  {
    "timestamp": "2025-10-08T19:58:11.700252",
    "latency_ms": 17.692464,
    "count": 14,
    "cache_miss": false,
    "keyword": "tyrannous"
  },
  {
    "timestamp": "2025-10-08T19:58:11.719826",
    "latency_ms": 14.086304,
    "count": 0,
    "cache_miss": false,
    "keyword": "Thine eyes"
  }
]