[
  {
    "timestamp": "2025-10-01T08:20:03.455745",
    "latency_ms": 15.829713,
    "count": 30526,
    "cache_miss": false,
    "keyword": "the"
  },
  {
    "timestamp": "2025-10-01T08:20:03.471941",
    "latency_ms": 12.945082,
    "count": 28566,
    "cache_miss": false,
    "keyword": "and"
  },
  {
    "timestamp": "2025-10-01T08:20:04.098385",
    "latency_ms": 623.071352,
    "count": 38,
    "cache_miss": false,
    "keyword": "Roses"
  },
  {
    "timestamp": "2025-10-01T08:20:04.154612",
    "latency_ms": 40.066942,
    "count": 57,
    "cache_miss": false,
    "keyword": "absence"
  },
  {
    "timestamp": "2025-10-01T08:20:05.669547",
    "latency_ms": 1504.7706,
    "count": 4,
    "cache_miss": false,
    "keyword": "withering"
  },
  {
    "timestamp": "2025-10-01T08:20:07.308320",
    "latency_ms": 1623.774528,
    "count": 0,
    "cache_miss": false,
    "keyword": "Thine eyes"
  },
  {
    "timestamp": "2025-10-01T08:20:07.377168",
    "latency_ms": 44.254196,
    "count": 94,
    "cache_miss": false,
    "keyword": "cheek"
  },
  {
    "timestamp": "2025-10-01T08:20:09.336195",
    "latency_ms": 1946.220075,
    "count": 2957,
    "cache_miss": false,
    "keyword": "she"
  },
  {
    "timestamp": "2025-10-01T08:20:09.599724",
    "latency_ms": 191.928801,
    "count": 30,
    "cache_miss": false,
    "keyword": "compare"
  },
  {
    "timestamp": "2025-10-01T08:20:09.756756",
    "latency_ms": 121.912978,
    "count": 14,
    "cache_miss": false,
    "keyword": "tyrannous"
  }
]