[
  {
    "timestamp": "2025-10-01T21:05:43.329981",
    "latency_ms": 17.670565,
    "count": 30526,
    "cache_miss": false,
    "keyword": "the"
  },
  {
    "timestamp": "2025-10-01T21:05:43.353239",
    "latency_ms": 17.231113,
    "count": 28566,
    "cache_miss": false,
    "keyword": "and"
  },
  {
    "timestamp": "2025-10-01T21:05:43.376560",
    "latency_ms": 17.89529,
    "count": 38,
    "cache_miss": false,
    "keyword": "Roses"
  },
  {
    "timestamp": "2025-10-01T21:05:43.400224",
    "latency_ms": 17.71677,
    "count": 57,
    "cache_miss": false,
    "keyword": "absence"
  },
  {
    "timestamp": "2025-10-01T21:05:43.423434",
    "latency_ms": 18.639777,
    "count": 4,
    "cache_miss": false,
    "keyword": "withering"
  },
  {
    "timestamp": "2025-10-01T21:05:43.448085",
    "latency_ms": 18.079913,
    "count": 0,
    "cache_miss": false,
    "keyword": "Thine eyes"
  },
  {
    "timestamp": "2025-10-01T21:05:43.471340",
    "latency_ms": 26.369081,
    "count": 94,
    "cache_miss": false,
    "keyword": "cheek"
  },
  {
    "timestamp": "2025-10-01T21:05:43.505731",
    "latency_ms": 23.221413,
    "count": 2957,
    "cache_miss": false,
    "keyword": "she"
  },
  {
    "timestamp": "2025-10-01T21:05:43.533922",
    "latency_ms": 24.371347,
    "count": 30,
    "cache_miss": false,
    "keyword": "compare"
  },
  {
    "timestamp": "2025-10-01T21:05:43.568374",
    "latency_ms": 17.646462,
    "count": 14,
    "cache_miss": false,
    "keyword": "tyrannous"
  }
]