[
  {
    "timestamp": "2025-10-01T19:54:03.698750",
    "latency_ms": 69.314124,
    "count": 30526,
    "cache_miss": false,
    "keyword": "the"
  },
  {
    "timestamp": "2025-10-01T19:54:03.796875",
    "latency_ms": 31.557852,
    "count": 28566,
    "cache_miss": false,
    "keyword": "and"
  },
  {
    "timestamp": "2025-10-01T19:54:03.850203",
    "latency_ms": 45.735569,
    "count": 38,
    "cache_miss": false,
    "keyword": "Roses"
  },
  {
    "timestamp": "2025-10-01T19:54:03.918444",
    "latency_ms": 57.808074,
    "count": 57,
    "cache_miss": false,
    "keyword": "absence"
  },
  {
    "timestamp": "2025-10-01T19:54:03.981015",
    "latency_ms": 34.758772,
    "count": 4,
    "cache_miss": false,
    "keyword": "withering"
  },
  {
    "timestamp": "2025-10-01T19:54:04.020437",
    "latency_ms": 41.14111,
    "count": 0,
    "cache_miss": false,
    "keyword": "Thine eyes"
  },
  {
    "timestamp": "2025-10-01T19:54:04.074001",
    "latency_ms": 22.548952,
    "count": 94,
    "cache_miss": false,
    "keyword": "cheek"
  },
  {
    "timestamp": "2025-10-01T19:54:04.107374",
    "latency_ms": 28.126009,
    "count": 2957,
    "cache_miss": false,
    "keyword": "she"
  },
  {
    "timestamp": "2025-10-01T19:54:04.143377",
    "latency_ms": 45.375932,
    "count": 30,
    "cache_miss": false,
    "keyword": "compare"
  },
  {
    "timestamp": "2025-10-01T19:54:04.194695",
    "latency_ms": 18.567955,
    "count": 14,
    "cache_miss": false,
    "keyword": "tyrannous"
  }
]