[
  {
    "timestamp": "2025-09-30T19:52:34.704412",
    "latency_ms": 20.399193,
    "count": 30526,
    "cache_miss": false,
    "keyword": "the"
  },
  {
    "timestamp": "2025-09-30T19:52:34.726436",
    "latency_ms": 17.991193,
    "count": 28566,
    "cache_miss": false,
    "keyword": "and"
  },
  {
    "timestamp": "2025-09-30T19:52:34.745664",
    "latency_ms": 15.848815,
    "count": 38,
    "cache_miss": false,
    "keyword": "Roses"
  },
  {
    "timestamp": "2025-09-30T19:52:34.759240",
    "latency_ms": 10.500871,
    "count": 57,
    "cache_miss": false,
    "keyword": "absence"
  },
  {
    "timestamp": "2025-09-30T19:52:35.885297",
    "latency_ms": 1124.641351,
    "count": 4,
    "cache_miss": false,
    "keyword": "withering"
  },
  {
    "timestamp": "2025-09-30T19:52:37.138047",
    "latency_ms": 1244.328588,
    "count": 0,
    "cache_miss": false,
    "keyword": "Thine eyes"
  },
  {
    "timestamp": "2025-09-30T19:52:38.493612",
    "latency_ms": 1349.906919,
    "count": 94,
    "cache_miss": false,
    "keyword": "cheek"
  },
  {
    "timestamp": "2025-09-30T19:52:41.003583",
    "latency_ms": 2498.359308,
    "count": 2957,
    "cache_miss": false,
    "keyword": "she"
  },
  {
    "timestamp": "2025-09-30T19:52:41.042838",
    "latency_ms": 29.912162,
    "count": 30,
    "cache_miss": false,
    "keyword": "compare"
  },
  {
    "timestamp": "2025-09-30T19:52:42.128246",
    "latency_ms": 1080.851085,
    "count": 14,
    "cache_miss": false,
    "keyword": "tyrannous"
  }
]