[
  {
    "timestamp": "2025-09-30T19:52:37.106693",
    "latency_ms": 775.621582,
    "count": 30526,
    "cache_miss": false,
    "keyword": "the"
  },
  {
    "timestamp": "2025-09-30T19:52:38.364792",
    "latency_ms": 1244.513629,
    "count": 28566,
    "cache_miss": false,
    "keyword": "and"
  },
  {
    "timestamp": "2025-09-30T19:52:38.419063",
    "latency_ms": 43.31041,
    "count": 38,
    "cache_miss": false,
    "keyword": "Roses"
  },
  {
    "timestamp": "2025-09-30T19:52:38.456997",
    "latency_ms": 27.159627,
    "count": 57,
    "cache_miss": false,
    "keyword": "absence"
  },
  {
    "timestamp": "2025-09-30T19:52:38.486420",
    "latency_ms": 21.317326,
    "count": 4,
    "cache_miss": false,
    "keyword": "withering"
  },
  {
    "timestamp": "2025-09-30T19:52:38.538976",
    "latency_ms": 42.191414,
    "count": 0,
    "cache_miss": false,
    "keyword": "Thine eyes"
  },
  {
    "timestamp": "2025-09-30T19:52:38.584252",
    "latency_ms": 33.62028,
    "count": 94,
    "cache_miss": false,
    "keyword": "cheek"
  },
  {
    "timestamp": "2025-09-30T19:52:40.959964",
    "latency_ms": 2371.480739,
    "count": 2957,
    "cache_miss": false,
    "keyword": "she"
  },
  {
    "timestamp": "2025-09-30T19:52:41.013340",
    "latency_ms": 39.324869,
    "count": 30,
    "cache_miss": false,
    "keyword": "compare"
  },
  {
    "timestamp": "2025-09-30T19:52:42.157414",
    "latency_ms": 1136.689268,
    "count": 14,
    "cache_miss": false,
    "keyword": "tyrannous"
  }
]