[
  {
    "timestamp": "2025-10-07T19:47:18.999118",
    "latency_ms": 2351.419279,
    "count": 30526,
    "cache_miss": false,
    "keyword": "the"
  },
  {
    "timestamp": "2025-10-07T19:47:21.358899",
    "latency_ms": 28.814562,
    "count": 28566,
    "cache_miss": false,
    "keyword": "and"
  },
  {
    "timestamp": "2025-10-07T19:47:21.407564",
    "latency_ms": 2535.585227,
    "count": 38,
    "cache_miss": false,
    "keyword": "Roses"
  },
  {
    "timestamp": "2025-10-07T19:47:23.950638",
    "latency_ms": 3468.79098,
    "count": 57,
    "cache_miss": false,
    "keyword": "absence"
  },
  {
    "timestamp": "2025-10-07T19:47:27.427868",
    "latency_ms": 1390.553049,
    "count": 4,
    "cache_miss": false,
    "keyword": "withering"
  },
  {
    "timestamp": "2025-10-07T19:47:28.861109",
    "latency_ms": 230.217134,
    "count": 0,
    "cache_miss": false,
    "keyword": "Thine eyes"
  },
  {
    "timestamp": "2025-10-07T19:47:29.123731",
    "latency_ms": 370.475394,
    "count": 94,
    "cache_miss": false,
    "keyword": "cheek"
  },
  {
    "timestamp": "2025-10-07T19:47:29.520840",
    "latency_ms": 287.731337,
    "count": 2957,
    "cache_miss": false,
    "keyword": "she"
  },
  {
    "timestamp": "2025-10-07T19:47:29.825939",
    "latency_ms": 233.499705,
    "count": 30,
    "cache_miss": false,
    "keyword": "compare"
  },
  {
    "timestamp": "2025-10-07T19:47:30.118576",
    "latency_ms": 339.239062,
    "count": 14,
    "cache_miss": false,
    "keyword": "tyrannous"
  }
]