[
  {
    "timestamp": "2025-10-07T20:03:22.762518",
    "latency_ms": 1120.846845,
    "count": 30526,
    "cache_miss": false,
    "keyword": "the"
  },
  {
    "timestamp": "2025-10-07T20:03:23.895692",
    "latency_ms": 42.663223,
    "count": 28566,
    "cache_miss": false,
    "keyword": "and"
  },
  {
    "timestamp": "2025-10-07T20:03:24.001526",
    "latency_ms": 1669.535755,
    "count": 38,
    "cache_miss": false,
    "keyword": "Roses"
  },
  {
    "timestamp": "2025-10-07T20:03:25.679121",
    "latency_ms": 52.891836,
    "count": 57,
    "cache_miss": false,
    "keyword": "absence"
  },
  {
    "timestamp": "2025-10-07T20:03:25.750009",
    "latency_ms": 52.065154,
    "count": 4,
    "cache_miss": false,
    "keyword": "withering"
  },
  {
    "timestamp": "2025-10-07T20:03:25.836026",
    "latency_ms": 78.788599,
    "count": 0,
    "cache_miss": false,
    "keyword": "Thine eyes"
  },
  {
    "timestamp": "2025-10-07T20:03:25.925655",
    "latency_ms": 89.197129,
    "count": 94,
    "cache_miss": false,
    "keyword": "cheek"
  },
  {
    "timestamp": "2025-10-07T20:03:26.028269",
    "latency_ms": 81.139831,
    "count": 2957,
    "cache_miss": false,
    "keyword": "she"
  },
  {
    "timestamp": "2025-10-07T20:03:26.127527",
    "latency_ms": 65.247558,
    "count": 30,
    "cache_miss": false,
    "keyword": "compare"
  },
  {
    "timestamp": "2025-10-07T20:03:26.206111",
    "latency_ms": 44.563811,
    "count": 14,
    "cache_miss": false,
    "keyword": "tyrannous"
  }
]