[
  {
    "timestamp": "2025-10-01T18:34:26.715676",
    "latency_ms": 9.971905,
    "count": 30526,
    "cache_miss": false,
    "keyword": "the"
  },
  {
    "timestamp": "2025-10-01T18:34:26.728831",
    "latency_ms": 13.819269,
    "count": 28566,
    "cache_miss": false,
    "keyword": "and"
  },
  {
    "timestamp": "2025-10-01T18:34:26.746823",
    "latency_ms": 13.271403,
    "count": 38,
    "cache_miss": false,
    "keyword": "Roses"
  },
  {
    "timestamp": "2025-10-01T18:34:26.763929",
    "latency_ms": 21.922948,
    "count": 57,
    "cache_miss": false,
    "keyword": "absence"
  },
  {
    "timestamp": "2025-10-01T18:34:26.790770",
    "latency_ms": 11.770622,
    "count": 4,
    "cache_miss": false,
    "keyword": "withering"
  },
  {
    "timestamp": "2025-10-01T18:34:26.808271",
    "latency_ms": 17.641731,
    "count": 0,
    "cache_miss": false,
    "keyword": "Thine eyes"
  },
  {
    "timestamp": "2025-10-01T18:34:26.829151",
    "latency_ms": 10.581778,
    "count": 94,
    "cache_miss": false,
    "keyword": "cheek"
  },
  {
    "timestamp": "2025-10-01T18:34:26.844696",
    "latency_ms": 1511.949732,
    "count": 2957,
    "cache_miss": true,
    "keyword": "she"
  },
  {
    "timestamp": "2025-10-01T18:34:28.364135",
    "latency_ms": 75.128475,
    "count": 30,
    "cache_miss": false,
    "keyword": "compare"
  },
  {
    "timestamp": "2025-10-01T18:34:28.490259",
    "latency_ms": 295.723421,
    "count": 14,
    "cache_miss": false,
    "keyword": "tyrannous"
  }
]