[
  {
    "timestamp": "2025-09-30T19:52:56.526344",
    "latency_ms": 45.44782,
    "count": 30526,
    "cache_miss": false,
    "keyword": "the"
  },
  {
    "timestamp": "2025-09-30T19:52:56.541070",
    "latency_ms": 11.578398,
    "count": 28566,
    "cache_miss": false,
    "keyword": "and"
  },
  {
    "timestamp": "2025-09-30T19:52:56.556264",
    "latency_ms": 10.635818,
    "count": 38,
    "cache_miss": false,
    "keyword": "Roses"
  },
  {
    "timestamp": "2025-09-30T19:52:56.570534",
    "latency_ms": 11.295575,
    "count": 57,
    "cache_miss": false,
    "keyword": "absence"
  },
  {
    "timestamp": "2025-09-30T19:52:56.592059",
    "latency_ms": 18.363184,
    "count": 4,
    "cache_miss": false,
    "keyword": "withering"
  },
  {
    "timestamp": "2025-09-30T19:52:56.611385",
    "latency_ms": 11.743413,
    "count": 0,
    "cache_miss": false,
    "keyword": "Thine eyes"
  },
  {
    "timestamp": "2025-09-30T19:52:56.648774",
    "latency_ms": 24.005971,
    "count": 94,
    "cache_miss": false,
    "keyword": "cheek"
  },
  {
    "timestamp": "2025-09-30T19:52:56.675102",
    "latency_ms": 22.84337,
    "count": 2957,
    "cache_miss": false,
    "keyword": "she"
  },
  {
    "timestamp": "2025-09-30T19:52:56.692671",
    "latency_ms": 14.284632,
    "count": 30,
    "cache_miss": false,
    "keyword": "compare"
  },
  {
    "timestamp": "2025-09-30T19:52:56.708879",
    "latency_ms": 11.70691,
    "count": 14,
    "cache_miss": false,
    "keyword": "tyrannous"
  }
]