[
  {
    "timestamp": "2025-09-30T21:09:20.579675",
    "latency_ms": 11.689216,
    "count": 30526,
    "cache_miss": false,
    "keyword": "the"
  },
  {
    "timestamp": "2025-09-30T21:09:20.593801",
    "latency_ms": 10.901353,
    "count": 28566,
    "cache_miss": false,
    "keyword": "and"
  },
  {
    "timestamp": "2025-09-30T21:09:20.608459",
    "latency_ms": 11.328687,
    "count": 38,
    "cache_miss": false,
    "keyword": "Roses"
  },
  {
    "timestamp": "2025-09-30T21:09:20.623814",
    "latency_ms": 11.039464,
    "count": 57,
    "cache_miss": false,
    "keyword": "absence"
  },
  {
    "timestamp": "2025-09-30T21:09:20.638681",
    "latency_ms": 11.424194,
    "count": 4,
    "cache_miss": false,
    "keyword": "withering"
  },
  {
    "timestamp": "2025-09-30T21:09:20.661645",
    "latency_ms": 11.530303,
    "count": 0,
    "cache_miss": false,
    "keyword": "Thine eyes"
  },
  {
    "timestamp": "2025-09-30T21:09:20.675204",
    "latency_ms": 10.513924,
    "count": 94,
    "cache_miss": false,
    "keyword": "cheek"
  },
  {
    "timestamp": "2025-09-30T21:09:20.692871",
    "latency_ms": 14.371225,
    "count": 2957,
    "cache_miss": false,
    "keyword": "she"
  },
  {
    "timestamp": "2025-09-30T21:09:20.706540",
    "latency_ms": 10.583928,
    "count": 30,
    "cache_miss": false,
    "keyword": "compare"
  },
  {
    "timestamp": "2025-09-30T21:09:20.724137",
    "latency_ms": 14.529337,
    "count": 14,
    "cache_miss": false,
    "keyword": "tyrannous"
  }
]