[
  {
    "timestamp": "2025-10-08T19:30:01.988313",
    "latency_ms": 4501.307266,
    "count": 30526,
    "cache_miss": false,
    "keyword": "the"
  },
  {
    "timestamp": "2025-10-08T19:30:06.513689",
    "latency_ms": 100.196971,
    "count": 28566,
    "cache_miss": false,
    "keyword": "and"
  },
  {
    "timestamp": "2025-10-08T19:30:06.616117",
    "latency_ms": 161.515934,
    "count": 2957,
    "cache_miss": false,
    "keyword": "she"
  },
  {
    "timestamp": "2025-10-08T19:30:06.794199",
    "latency_ms": 82.164958,
    "count": 94,
    "cache_miss": false,
    "keyword": "cheek"
  },
  {
    "timestamp": "2025-10-08T19:30:06.894337",
    "latency_ms": 95.441792,
    "count": 38,
    "cache_miss": false,
    "keyword": "Roses"
  },
  {
    "timestamp": "2025-10-08T19:30:07.009713",
    "latency_ms": 120.247286,
    "count": 57,
    "cache_miss": false,
    "keyword": "absence"
  },
  {
    "timestamp": "2025-10-08T19:30:07.158292",
    "latency_ms": 148.937669,
    "count": 30,
    "cache_miss": false,
    "keyword": "compare"
  },
  {
    "timestamp": "2025-10-08T19:30:07.336672",
    "latency_ms": 149.964372,
    "count": 4,
    "cache_miss": false,
    "keyword": "withering"
  },
  {
    "timestamp": "2025-10-08T19:30:07.544302",
    "latency_ms": 152.365214,
    "count": 14,
    "cache_miss": false,
    "keyword": "tyrannous"
  },
  {
    "timestamp": "2025-10-08T19:30:07.724297",
    "latency_ms": 71.190655,
    "count": 0,
    "cache_miss": false,
    "keyword": "Thine eyes"
  }
]