[
  {
    "timestamp": "2025-10-01T08:32:38.923364",
    "latency_ms": 1129.508254,
    "count": 30526,
    "cache_miss": false,
    "keyword": "the"
  },
  {
    "timestamp": "2025-10-01T08:32:40.421003",
    "latency_ms": 1485.128296,
    "count": 28566,
    "cache_miss": false,
    "keyword": "and"
  },
  {
    "timestamp": "2025-10-01T08:32:42.119988",
    "latency_ms": 1658.284064,
    "count": 38,
    "cache_miss": false,
    "keyword": "Roses"
  },
  {
    "timestamp": "2025-10-01T08:32:42.273433",
    "latency_ms": 109.625611,
    "count": 57,
    "cache_miss": false,
    "keyword": "absence"
  },
  {
    "timestamp": "2025-10-01T08:32:42.330874",
    "latency_ms": 40.859786,
    "count": 4,
    "cache_miss": false,
    "keyword": "withering"
  },
  {
    "timestamp": "2025-10-01T08:32:42.363256",
    "latency_ms": 20.950705,
    "count": 0,
    "cache_miss": false,
    "keyword": "Thine eyes"
  },
  {
    "timestamp": "2025-10-01T08:32:42.383293",
    "latency_ms": 15.605167,
    "count": 94,
    "cache_miss": false,
    "keyword": "cheek"
  },
  {
    "timestamp": "2025-10-01T08:32:44.029266",
    "latency_ms": 1641.551121,
    "count": 2957,
    "cache_miss": false,
    "keyword": "she"
  },
  {
    "timestamp": "2025-10-01T08:32:46.099627",
    "latency_ms": 2035.821875,
    "count": 30,
    "cache_miss": false,
    "keyword": "compare"
  },
  {
    "timestamp": "2025-10-01T08:32:46.551835",
    "latency_ms": 238.921274,
    "count": 14,
    "cache_miss": false,
    "keyword": "tyrannous"
  }
]