[
  {
    "timestamp": "2025-10-08T19:34:28.893340",
    "latency_ms": 26.863224,
    "count": 30526,
    "cache_miss": false,
    "keyword": "the"
  },
  {
    "timestamp": "2025-10-08T19:34:28.923705",
    "latency_ms": 19.259013,
    "count": 28566,
    "cache_miss": false,
    "keyword": "and"
  },
  {
    "timestamp": "2025-10-08T19:34:28.946977",
    "latency_ms": 20.757532,
    "count": 2957,
    "cache_miss": false,
    "keyword": "she"
  },
  {
    "timestamp": "2025-10-08T19:34:28.970816",
    "latency_ms": 41.514164,
    "count": 94,
    "cache_miss": false,
    "keyword": "cheek"
  },
  {
    "timestamp": "2025-10-08T19:34:29.014986",
    "latency_ms": 14.987989,
    "count": 38,
    "cache_miss": false,
    "keyword": "Roses"
  },
  {
    "timestamp": "2025-10-08T19:34:29.035218",
    "latency_ms": 15.515067,
    "count": 57,
    "cache_miss": false,
    "keyword": "absence"
  },
  {
    "timestamp": "2025-10-08T19:34:29.053211",
    "latency_ms": 25.05406,
    "count": 30,
    "cache_miss": false,
    "keyword": "compare"
  },
  {
    "timestamp": "2025-10-08T19:34:29.080746",
    "latency_ms": 35.642506,
    "count": 4,
    "cache_miss": false,
    "keyword": "withering"
  },
  {
    "timestamp": "2025-10-08T19:34:29.118911",
    "latency_ms": 23.084872,
    "count": 14,
    "cache_miss": false,
    "keyword": "tyrannous"
  },
  {
    "timestamp": "2025-10-08T19:34:29.144112",
    "latency_ms": 15.135011,
    "count": 0,
    "cache_miss": false,
    "keyword": "Thine eyes"
  }
]