[
  {
    "timestamp": "2025-10-07T21:50:12.576112",
    "latency_ms": 17.151159,
    "count": 30526,
    "cache_miss": false,
    "keyword": "the"
  },
  {
    "timestamp": "2025-10-07T21:50:12.595326",
    "latency_ms": 10.64513,
    "count": 28566,
    "cache_miss": false,
    "keyword": "and"
  },
  {
    "timestamp": "2025-10-07T21:50:12.607844",
    "latency_ms": 10.96646,
    "count": 38,
    "cache_miss": false,
    "keyword": "Roses"
  },
  {
    "timestamp": "2025-10-07T21:50:12.620690",
    "latency_ms": 14.340287,
    "count": 57,
    "cache_miss": false,
    "keyword": "absence"
  },
  {
    "timestamp": "2025-10-07T21:50:12.636915",
    "latency_ms": 26.327345,
    "count": 4,
    "cache_miss": false,
    "keyword": "withering"
  },
  {
    "timestamp": "2025-10-07T21:50:12.665156",
    "latency_ms": 11.392802,
    "count": 0,
    "cache_miss": false,
    "keyword": "Thine eyes"
  },
  {
    "timestamp": "2025-10-07T21:50:12.679588",
    "latency_ms": 10.644429,
    "count": 94,
    "cache_miss": false,
    "keyword": "cheek"
  },
  {
    "timestamp": "2025-10-07T21:50:12.692308",
    "latency_ms": 10.526917,
    "count": 2957,
    "cache_miss": false,
    "keyword": "she"
  },
  {
    "timestamp": "2025-10-07T21:50:12.704724",
    "latency_ms": 10.523618,
    "count": 30,
    "cache_miss": false,
    "keyword": "compare"
  },
  {
    "timestamp": "2025-10-07T21:50:12.717204",
    "latency_ms": 11.236387,
    "count": 14,
    "cache_miss": false,
    "keyword": "tyrannous"
  }
]