[
  {
    "timestamp": "2025-09-27T10:38:13.591599",
    "latency_ms": 112.796827,
    "count": 30526,
    "cache_miss": false,
    "keyword": "the"
  },
  {
    "timestamp": "2025-09-27T10:38:14.263095",
    "latency_ms": 669.318708,
    "count": 28566,
    "cache_miss": true,
    "keyword": "and"
  },
  {
    "timestamp": "2025-09-27T10:38:15.187198",
    "latency_ms": 922.057803,
    "count": 38,
    "cache_miss": false,
    "keyword": "Roses"
  },
  {
    "timestamp": "2025-09-27T10:38:16.320207",
    "latency_ms": 1126.125353,
    "count": 57,
    "cache_miss": false,
    "keyword": "absence"
  },
  {
    "timestamp": "2025-09-27T10:38:17.446762",
    "latency_ms": 1123.714907,
    "count": 4,
    "cache_miss": false,
    "keyword": "withering"
  },
  {
    "timestamp": "2025-09-27T10:38:19.963790",
    "latency_ms": 2510.02401,
    "count": 0,
    "cache_miss": false,
    "keyword": "Thine eyes"
  },
  {
    "timestamp": "2025-09-27T10:38:20.045954",
    "latency_ms": 66.49034,
    "count": 94,
    "cache_miss": false,
    "keyword": "cheek"
  },
  {
    "timestamp": "2025-09-27T10:38:21.250345",
    "latency_ms": 1186.82299,
    "count": 2957,
    "cache_miss": false,
    "keyword": "she"
  },
  {
    "timestamp": "2025-09-27T10:38:22.828099",
    "latency_ms": 1562.44979,
    "count": 30,
    "cache_miss": false,
    "keyword": "compare"
  },
  {
    "timestamp": "2025-09-27T10:38:24.380156",
    "latency_ms": 1547.280382,
    "count": 14,
    "cache_miss": false,
    "keyword": "tyrannous"
  }
]