[
  {
    "timestamp": "2025-10-08T19:33:53.383285",
    "latency_ms": 3053.492793,
    "count": 30526,
    "cache_miss": false,
    "keyword": "the"
  },
  {
    "timestamp": "2025-10-08T19:33:56.446100",
    "latency_ms": 2682.724471,
    "count": 28566,
    "cache_miss": false,
    "keyword": "and"
  },
  {
    "timestamp": "2025-10-08T19:33:59.152754",
    "latency_ms": 128.743729,
    "count": 2957,
    "cache_miss": false,
    "keyword": "she"
  },
  {
    "timestamp": "2025-10-08T19:33:59.308020",
    "latency_ms": 4448.965166,
    "count": 94,
    "cache_miss": false,
    "keyword": "cheek"
  },
  {
    "timestamp": "2025-10-08T19:34:03.784228",
    "latency_ms": 5704.411785,
    "count": 38,
    "cache_miss": false,
    "keyword": "Roses"
  },
  {
    "timestamp": "2025-10-08T19:34:09.650566",
    "latency_ms": 17.912812,
    "count": 57,
    "cache_miss": false,
    "keyword": "absence"
  },
  {
    "timestamp": "2025-10-08T19:34:09.670877",
    "latency_ms": 16.892169,
    "count": 30,
    "cache_miss": false,
    "keyword": "compare"
  },
  {
    "timestamp": "2025-10-08T19:34:09.690298",
    "latency_ms": 27.219017,
    "count": 4,
    "cache_miss": false,
    "keyword": "withering"
  },
  {
    "timestamp": "2025-10-08T19:34:09.720397",
    "latency_ms": 15.883628,
    "count": 14,
    "cache_miss": false,
    "keyword": "tyrannous"
  },
  {
    "timestamp": "2025-10-08T19:34:09.738704",
    "latency_ms": 25.090119,
    "count": 0,
    "cache_miss": false,
    "keyword": "Thine eyes"
  }
]