[
  {
    "timestamp": "2025-10-08T19:52:42.615493",
    "latency_ms": 14.500338,
    "count": 30526,
    "cache_miss": false,
    "keyword": "the"
  },
  {
    "timestamp": "2025-10-08T19:52:42.632354",
    "latency_ms": 4701.133053,
    "count": 28566,
    "cache_miss": false,
    "keyword": "and"
  },
  {
    "timestamp": "2025-10-08T19:52:47.347093",
    "latency_ms": 171.363484,
    "count": 2957,
    "cache_miss": false,
    "keyword": "she"
  },
  {
    "timestamp": "2025-10-08T19:52:47.548085",
    "latency_ms": 253.186266,
    "count": 94,
    "cache_miss": false,
    "keyword": "cheek"
  },
  {
    "timestamp": "2025-10-08T19:52:47.838175",
    "latency_ms": 2820.798878,
    "count": 38,
    "cache_miss": false,
    "keyword": "Roses"
  },
  {
    "timestamp": "2025-10-08T19:52:50.670808",
    "latency_ms": 1860.534203,
    "count": 57,
    "cache_miss": false,
    "keyword": "absence"
  },
  {
    "timestamp": "2025-10-08T19:52:52.566143",
    "latency_ms": 307.712277,
    "count": 30,
    "cache_miss": false,
    "keyword": "compare"
  },
  {
    "timestamp": "2025-10-08T19:52:52.895224",
    "latency_ms": 1284.167138,
    "count": 4,
    "cache_miss": false,
    "keyword": "withering"
  },
  {
    "timestamp": "2025-10-08T19:52:54.215139",
    "latency_ms": 146.458838,
    "count": 14,
    "cache_miss": false,
    "keyword": "tyrannous"
  },
  {
    "timestamp": "2025-10-08T19:52:54.407573",
    "latency_ms": 186.801576,
    "count": 0,
    "cache_miss": false,
    "keyword": "Thine eyes"
  }
]