[
  {
    "timestamp": "2025-10-01T19:50:44.050525",
    "latency_ms": 16.959853,
    "count": 30526,
    "cache_miss": false,
    "keyword": "the"
  },
  {
    "timestamp": "2025-10-01T19:50:44.070808",
    "latency_ms": 10.746001,
    "count": 28566,
    "cache_miss": false,
    "keyword": "and"
  },
  {
    "timestamp": "2025-10-01T19:50:44.084758",
    "latency_ms": 11.584702,
    "count": 38,
    "cache_miss": false,
    "keyword": "Roses"
  },
  {
    "timestamp": "2025-10-01T19:50:44.102208",
    "latency_ms": 16.418488,
    "count": 57,
    "cache_miss": false,
    "keyword": "absence"
  },
  {
    "timestamp": "2025-10-01T19:50:44.121958",
    "latency_ms": 13.88038,
    "count": 4,
    "cache_miss": false,
    "keyword": "withering"
  },
  {
    "timestamp": "2025-10-01T19:50:44.139716",
    "latency_ms": 17.458913,
    "count": 0,
    "cache_miss": false,
    "keyword": "Thine eyes"
  },
  {
    "timestamp": "2025-10-01T19:50:44.162374",
    "latency_ms": 10.934824,
    "count": 94,
    "cache_miss": false,
    "keyword": "cheek"
  },
  {
    "timestamp": "2025-10-01T19:50:44.178790",
    "latency_ms": 11.014833,
    "count": 2957,
    "cache_miss": false,
    "keyword": "she"
  },
  {
    "timestamp": "2025-10-01T19:50:44.194876",
    "latency_ms": 15.319954,
    "count": 30,
    "cache_miss": false,
    "keyword": "compare"
  },
  {
    "timestamp": "2025-10-01T19:50:44.213588",
    "latency_ms": 11.06954,
    "count": 14,
    "cache_miss": false,
    "keyword": "tyrannous"
  }
]