[
  {
    "timestamp": "2025-10-01T19:50:00.611900",
    "latency_ms": 9.351816,
    "count": 30526,
    "cache_miss": false,
    "keyword": "the"
  },
  {
    "timestamp": "2025-10-01T19:50:00.624966",
    "latency_ms": 7.928961,
    "count": 28566,
    "cache_miss": false,
    "keyword": "and"
  },
  {
    "timestamp": "2025-10-01T19:50:00.635771",
    "latency_ms": 616.242714,
    "count": 38,
    "cache_miss": false,
    "keyword": "Roses"
  },
  {
    "timestamp": "2025-10-01T19:50:01.282045",
    "latency_ms": 30.634326,
    "count": 57,
    "cache_miss": false,
    "keyword": "absence"
  },
  {
    "timestamp": "2025-10-01T19:50:01.324389",
    "latency_ms": 1332.369272,
    "count": 4,
    "cache_miss": false,
    "keyword": "withering"
  },
  {
    "timestamp": "2025-10-01T19:50:02.672252",
    "latency_ms": 1237.406961,
    "count": 0,
    "cache_miss": false,
    "keyword": "Thine eyes"
  },
  {
    "timestamp": "2025-10-01T19:50:03.971075",
    "latency_ms": 166.288056,
    "count": 94,
    "cache_miss": false,
    "keyword": "cheek"
  },
  {
    "timestamp": "2025-10-01T19:50:04.230207",
    "latency_ms": 139.925993,
    "count": 2957,
    "cache_miss": false,
    "keyword": "she"
  },
  {
    "timestamp": "2025-10-01T19:50:04.419611",
    "latency_ms": 203.81123,
    "count": 30,
    "cache_miss": false,
    "keyword": "compare"
  },
  {
    "timestamp": "2025-10-01T19:50:04.650618",
    "latency_ms": 96.786009,
    "count": 14,
    "cache_miss": false,
    "keyword": "tyrannous"
  }
]